[
  {
    "full_name": "liquibase/liquibase",
    "stargazers_count": 4130,
    "open_issues_count": 650,
    "forks_count": 1742
  },
  {
    "full_name": "tinyhttp/tinyhttp",
    "stargazers_count": 2531,
    "open_issues_count": 9,
    "forks_count": 120
  },
  {
    "full_name": "liquibase/node-liquibase",
    "stargazers_count": 29,
    "open_issues_count": 14,
    "forks_count": 11
  },
  {
    "full_name": "open-sauced/open-sauced",
    "stargazers_count": 896,
    "open_issues_count": 0,
    "forks_count": 751
  }
]