[
  {
    "full_name": "smith-xyz/liquibase",
    "stargazers_count": 1,
    "open_issues_count": 0,
    "forks_count": 0
  },
  {
    "full_name": "guyroyse/dnd-and-graph-databases",
    "stargazers_count": 84,
    "open_issues_count": 0,
    "forks_count": 5
  },
  {
    "full_name": "testing-library/react-testing-library",
    "stargazers_count": 17128,
    "open_issues_count": 21,
    "forks_count": 1019
  },
  {
    "full_name": "testing-library/jest-dom",
    "stargazers_count": 3621,
    "open_issues_count": 84,
    "forks_count": 297
  }
]